{"slug":"autochat","route":"/tools/autochat","index":true,"seo":{"title":"Autochat — AI Ecommerce Tool","description":"Autochat: WhatsApp automation platform with no-code chatbots and eCommerce integration. Generate, review and debug code with Autochat. Free plan available.","schema_types":["SoftwareApplication","Product"]},"hero":{"name":"Autochat","tagline":"AI automation tool to debug code","logo_url":"https://logo.clearbit.com/autochat.in","logo_domain":"autochat.in","website_url":"https://autochat.in","pricing_tier":"freemium","score_overall":46,"is_featured":false},"taxonomy":{"category":"ai-marketing","subcategory":null,"microcategory":null,"use_cases":["debug-code","create-product-descriptions","Generate, review and debug code with Autochat","Write product descriptions at scale with Autochat","Build and deploy AI chatbots with Autochat"],"capabilities":["automation","debugging"],"industries":["ecommerce","marketing","E-Commerce"],"integrations":["whatsapp"],"ai_models":[],"platforms":["No-Code"],"audiences":["Developers"],"skill_levels":[]},"commercial":{"pricing_tier":"freemium","freemium":true,"free_trial":false,"affiliate_url":null,"partnerstack_match":false,"pricing_url":null,"signup_url":null,"monetization_score":0},"reviews":{"rating_average":null,"review_count_total":null,"g2_rating":null,"capterra_rating":null},"scores":{"overall":46,"content_readiness":97,"compare_value":null,"bestof_value":null,"beginner_fit":null,"integration_strength":null,"taxonomy_confidence":49},"content":{"description":"WhatsApp automation platform with no-code chatbots and eCommerce integration.","tags":["product-descriptions","chatbot","ecommerce","automation","marketing","no-code","Chat / Q&A","E-Commerce"],"feature_tags":["No-Code"]},"related":{"related_tools":[{"slug":"igleads","name":"Igleads","category":"ai-marketing","subcategory":"social-media","microcategory":null,"pricing_tier":"freemium","logo_url":"https://logo.clearbit.com/igleads.io","logo_domain":"igleads.io","website_url":"https://igleads.io/","score_overall":58,"is_featured":false},{"slug":"enalito-2-0","name":"Enalito 2","category":"ai-marketing","subcategory":"email-marketing","microcategory":"email-sequencing","pricing_tier":"freemium","logo_url":"https://logo.clearbit.com/enalito.com","logo_domain":"enalito.com","website_url":"https://enalito.com","score_overall":55,"is_featured":false},{"slug":"instant-programmatic-seo","name":"Instant Programmatic Seo","category":"ai-marketing","subcategory":"cro-landing-pages","microcategory":null,"pricing_tier":"freemium","logo_url":"https://logo.clearbit.com/instantpseo.com","logo_domain":"instantpseo.com","website_url":"https://www.instantpseo.com","score_overall":52,"is_featured":false},{"slug":"sparkle-5","name":"Sparkle","category":"ai-marketing","subcategory":"seo-tools","microcategory":null,"pricing_tier":"freemium","logo_url":"https://logo.clearbit.com/sparkleapp.com","logo_domain":"sparkleapp.com","website_url":"https://sparkleapp.com","score_overall":53,"is_featured":false},{"slug":"swifterm-com","name":"Swifterm","category":"ai-marketing","subcategory":"email-marketing","microcategory":"email-sequencing","pricing_tier":"freemium","logo_url":"https://logo.clearbit.com/swifterm.com","logo_domain":"swifterm.com","website_url":"https://swifterm.com","score_overall":55,"is_featured":false},{"slug":"10xbeast","name":"10xbeast","category":"ai-marketing","subcategory":"email-marketing","microcategory":"email-sequencing","pricing_tier":"freemium","logo_url":"https://logo.clearbit.com/10xbeast.com","logo_domain":"10xbeast.com","website_url":"https://10xbeast.com/","score_overall":57,"is_featured":false},{"slug":"10xengage","name":"10xengage","category":"ai-marketing","subcategory":"email-marketing","microcategory":"email-sequencing","pricing_tier":"freemium","logo_url":"https://logo.clearbit.com/10xengage.com","logo_domain":"10xengage.com","website_url":"https://10xengage.com","score_overall":51,"is_featured":false},{"slug":"acquation","name":"Acquation","category":"ai-marketing","subcategory":null,"microcategory":null,"pricing_tier":"freemium","logo_url":"https://logo.clearbit.com/acquation.com","logo_domain":"acquation.com","website_url":"https://acquation.com","score_overall":52,"is_featured":false}],"compare_candidates":[{"slug":"igleads","name":"Igleads","category":"ai-marketing","subcategory":"social-media","microcategory":null,"pricing_tier":"freemium","logo_url":"https://logo.clearbit.com/igleads.io","logo_domain":"igleads.io","website_url":"https://igleads.io/","score_overall":58,"is_featured":false},{"slug":"enalito-2-0","name":"Enalito 2","category":"ai-marketing","subcategory":"email-marketing","microcategory":"email-sequencing","pricing_tier":"freemium","logo_url":"https://logo.clearbit.com/enalito.com","logo_domain":"enalito.com","website_url":"https://enalito.com","score_overall":55,"is_featured":false},{"slug":"instant-programmatic-seo","name":"Instant Programmatic Seo","category":"ai-marketing","subcategory":"cro-landing-pages","microcategory":null,"pricing_tier":"freemium","logo_url":"https://logo.clearbit.com/instantpseo.com","logo_domain":"instantpseo.com","website_url":"https://www.instantpseo.com","score_overall":52,"is_featured":false},{"slug":"sparkle-5","name":"Sparkle","category":"ai-marketing","subcategory":"seo-tools","microcategory":null,"pricing_tier":"freemium","logo_url":"https://logo.clearbit.com/sparkleapp.com","logo_domain":"sparkleapp.com","website_url":"https://sparkleapp.com","score_overall":53,"is_featured":false},{"slug":"swifterm-com","name":"Swifterm","category":"ai-marketing","subcategory":"email-marketing","microcategory":"email-sequencing","pricing_tier":"freemium","logo_url":"https://logo.clearbit.com/swifterm.com","logo_domain":"swifterm.com","website_url":"https://swifterm.com","score_overall":55,"is_featured":false},{"slug":"10xbeast","name":"10xbeast","category":"ai-marketing","subcategory":"email-marketing","microcategory":"email-sequencing","pricing_tier":"freemium","logo_url":"https://logo.clearbit.com/10xbeast.com","logo_domain":"10xbeast.com","website_url":"https://10xbeast.com/","score_overall":57,"is_featured":false}],"alternatives":[{"slug":"igleads","name":"Igleads","category":"ai-marketing","subcategory":"social-media","microcategory":null,"pricing_tier":"freemium","logo_url":"https://logo.clearbit.com/igleads.io","logo_domain":"igleads.io","website_url":"https://igleads.io/","score_overall":58,"is_featured":false},{"slug":"enalito-2-0","name":"Enalito 2","category":"ai-marketing","subcategory":"email-marketing","microcategory":"email-sequencing","pricing_tier":"freemium","logo_url":"https://logo.clearbit.com/enalito.com","logo_domain":"enalito.com","website_url":"https://enalito.com","score_overall":55,"is_featured":false},{"slug":"instant-programmatic-seo","name":"Instant Programmatic Seo","category":"ai-marketing","subcategory":"cro-landing-pages","microcategory":null,"pricing_tier":"freemium","logo_url":"https://logo.clearbit.com/instantpseo.com","logo_domain":"instantpseo.com","website_url":"https://www.instantpseo.com","score_overall":52,"is_featured":false},{"slug":"sparkle-5","name":"Sparkle","category":"ai-marketing","subcategory":"seo-tools","microcategory":null,"pricing_tier":"freemium","logo_url":"https://logo.clearbit.com/sparkleapp.com","logo_domain":"sparkleapp.com","website_url":"https://sparkleapp.com","score_overall":53,"is_featured":false},{"slug":"swifterm-com","name":"Swifterm","category":"ai-marketing","subcategory":"email-marketing","microcategory":"email-sequencing","pricing_tier":"freemium","logo_url":"https://logo.clearbit.com/swifterm.com","logo_domain":"swifterm.com","website_url":"https://swifterm.com","score_overall":55,"is_featured":false},{"slug":"10xbeast","name":"10xbeast","category":"ai-marketing","subcategory":"email-marketing","microcategory":"email-sequencing","pricing_tier":"freemium","logo_url":"https://logo.clearbit.com/10xbeast.com","logo_domain":"10xbeast.com","website_url":"https://10xbeast.com/","score_overall":57,"is_featured":false}]}}