{"slug":"aysa-ai","route":"/tools/aysa-ai","index":true,"seo":{"title":"Aysa Ai — AI Marketing Tool","description":"Aysa Ai is an AI marketing SaaS for e-commerce, automating SEO, traffic, and sales. Explore features, freemium pricing, and how it boosts your business.","schema_types":["SoftwareApplication","Product"]},"hero":{"name":"Aysa Ai","tagline":"AI automation tool to write seo articles","logo_url":"https://logo.clearbit.com/aysa.ai","logo_domain":"aysa.ai","website_url":"https://www.aysa.ai","pricing_tier":"freemium","score_overall":55,"is_featured":false},"taxonomy":{"category":"ai-marketing","subcategory":null,"microcategory":null,"use_cases":["write-seo-articles","Improve SEO content rankings with Aysa Ai","Automate sales outreach and lead gen with Aysa Ai"],"capabilities":["automation","outreach-generation"],"industries":["marketing","saas","sales","software-development"],"integrations":[],"ai_models":[],"platforms":["Web"],"audiences":["Marketers","Sales Professionals"],"skill_levels":[]},"commercial":{"pricing_tier":"freemium","freemium":true,"free_trial":false,"affiliate_url":null,"partnerstack_match":false,"pricing_url":null,"signup_url":null,"monetization_score":0},"reviews":{"rating_average":null,"review_count_total":null,"g2_rating":null,"capterra_rating":null},"scores":{"overall":55,"content_readiness":96,"compare_value":null,"bestof_value":null,"beginner_fit":null,"integration_strength":null,"taxonomy_confidence":43},"content":{"description":"SaaS SEO automation software for e-commerce, using AI to boost traffic and sales.","tags":["seo","automation","sales","marketing","outreach","ecommerce","SEO & Keywords","E-Commerce"],"feature_tags":[],"long_description":"Aysa Ai is a specialized SaaS SEO automation software designed for e-commerce businesses. It leverages artificial intelligence to significantly boost website traffic and increase sales. This tool helps online stores streamline their SEO efforts and automate key marketing processes.","unique_features":["SaaS SEO automation for e-commerce","AI-powered traffic boosting","Automated sales generation","AI-driven SEO article writing","Automated sales outreach and lead generation"],"core_features":["Automate e-commerce SEO","Boost website traffic with AI","Increase online sales","Write SEO-optimized articles","Improve content rankings","Generate sales outreach","Automate lead generation"],"pros":["Automates core SEO tasks for efficiency","Specifically designed to boost traffic and sales for e-commerce","Offers a freemium pricing model for accessibility","Includes capabilities for sales outreach and lead generation"],"cons":["No known integrations with other platforms","Primarily focused on e-commerce, potentially limiting broader application","Limited public information on advanced customization or reporting features"]},"related":{"related_tools":[{"slug":"10xbeast","name":"10xbeast","category":"ai-marketing","subcategory":"email-marketing","microcategory":"email-sequencing","pricing_tier":"freemium","logo_url":"https://logo.clearbit.com/10xbeast.com","logo_domain":"10xbeast.com","website_url":"https://10xbeast.com/","score_overall":57,"is_featured":false},{"slug":"10xengage","name":"10xengage","category":"ai-marketing","subcategory":"email-marketing","microcategory":"email-sequencing","pricing_tier":"freemium","logo_url":"https://logo.clearbit.com/10xengage.com","logo_domain":"10xengage.com","website_url":"https://10xengage.com","score_overall":51,"is_featured":false},{"slug":"aindleads-ai-finds-leads","name":"Aindleads Ai Finds Leads","category":"ai-marketing","subcategory":null,"microcategory":null,"pricing_tier":"freemium","logo_url":"https://logo.clearbit.com/aindleads.com","logo_domain":"aindleads.com","website_url":"https://www.aindleads.com","score_overall":55,"is_featured":false},{"slug":"atonce","name":"Atonce","category":"ai-marketing","subcategory":null,"microcategory":null,"pricing_tier":"freemium","logo_url":"https://logo.clearbit.com/atonce.com","logo_domain":"atonce.com","website_url":"https://atonce.com","score_overall":58,"is_featured":false},{"slug":"b2b-rocket","name":"B2b Rocket","category":"ai-marketing","subcategory":"cro-landing-pages","microcategory":null,"pricing_tier":"freemium","logo_url":"https://logo.clearbit.com/b2brocket.ai","logo_domain":"b2brocket.ai","website_url":"https://get.b2brocket.ai/plgxl20y3nqf","score_overall":56,"is_featured":false},{"slug":"backlink-management","name":"Backlink Management","category":"ai-marketing","subcategory":"social-media","microcategory":null,"pricing_tier":"freemium","logo_url":"https://logo.clearbit.com/backlinkmanagement.io","logo_domain":"backlinkmanagement.io","website_url":"https://backlinkmanagement.io","score_overall":58,"is_featured":false},{"slug":"backlinker-ai","name":"Backlinker Ai","category":"ai-marketing","subcategory":null,"microcategory":null,"pricing_tier":"freemium","logo_url":"https://logo.clearbit.com/backlinker.ai","logo_domain":"backlinker.ai","website_url":"https://backlinker.ai","score_overall":52,"is_featured":false},{"slug":"calcleads","name":"Calcleads","category":"ai-marketing","subcategory":null,"microcategory":null,"pricing_tier":"freemium","logo_url":"https://logo.clearbit.com/calcleads.com","logo_domain":"calcleads.com","website_url":"https://calcleads.com","score_overall":54,"is_featured":false}],"compare_candidates":[{"slug":"10xbeast","name":"10xbeast","category":"ai-marketing","subcategory":"email-marketing","microcategory":"email-sequencing","pricing_tier":"freemium","logo_url":"https://logo.clearbit.com/10xbeast.com","logo_domain":"10xbeast.com","website_url":"https://10xbeast.com/","score_overall":57,"is_featured":false},{"slug":"10xengage","name":"10xengage","category":"ai-marketing","subcategory":"email-marketing","microcategory":"email-sequencing","pricing_tier":"freemium","logo_url":"https://logo.clearbit.com/10xengage.com","logo_domain":"10xengage.com","website_url":"https://10xengage.com","score_overall":51,"is_featured":false},{"slug":"aindleads-ai-finds-leads","name":"Aindleads Ai Finds Leads","category":"ai-marketing","subcategory":null,"microcategory":null,"pricing_tier":"freemium","logo_url":"https://logo.clearbit.com/aindleads.com","logo_domain":"aindleads.com","website_url":"https://www.aindleads.com","score_overall":55,"is_featured":false},{"slug":"atonce","name":"Atonce","category":"ai-marketing","subcategory":null,"microcategory":null,"pricing_tier":"freemium","logo_url":"https://logo.clearbit.com/atonce.com","logo_domain":"atonce.com","website_url":"https://atonce.com","score_overall":58,"is_featured":false},{"slug":"b2b-rocket","name":"B2b Rocket","category":"ai-marketing","subcategory":"cro-landing-pages","microcategory":null,"pricing_tier":"freemium","logo_url":"https://logo.clearbit.com/b2brocket.ai","logo_domain":"b2brocket.ai","website_url":"https://get.b2brocket.ai/plgxl20y3nqf","score_overall":56,"is_featured":false},{"slug":"backlink-management","name":"Backlink Management","category":"ai-marketing","subcategory":"social-media","microcategory":null,"pricing_tier":"freemium","logo_url":"https://logo.clearbit.com/backlinkmanagement.io","logo_domain":"backlinkmanagement.io","website_url":"https://backlinkmanagement.io","score_overall":58,"is_featured":false}],"alternatives":[{"slug":"10xbeast","name":"10xbeast","category":"ai-marketing","subcategory":"email-marketing","microcategory":"email-sequencing","pricing_tier":"freemium","logo_url":"https://logo.clearbit.com/10xbeast.com","logo_domain":"10xbeast.com","website_url":"https://10xbeast.com/","score_overall":57,"is_featured":false},{"slug":"10xengage","name":"10xengage","category":"ai-marketing","subcategory":"email-marketing","microcategory":"email-sequencing","pricing_tier":"freemium","logo_url":"https://logo.clearbit.com/10xengage.com","logo_domain":"10xengage.com","website_url":"https://10xengage.com","score_overall":51,"is_featured":false},{"slug":"aindleads-ai-finds-leads","name":"Aindleads Ai Finds Leads","category":"ai-marketing","subcategory":null,"microcategory":null,"pricing_tier":"freemium","logo_url":"https://logo.clearbit.com/aindleads.com","logo_domain":"aindleads.com","website_url":"https://www.aindleads.com","score_overall":55,"is_featured":false},{"slug":"atonce","name":"Atonce","category":"ai-marketing","subcategory":null,"microcategory":null,"pricing_tier":"freemium","logo_url":"https://logo.clearbit.com/atonce.com","logo_domain":"atonce.com","website_url":"https://atonce.com","score_overall":58,"is_featured":false},{"slug":"b2b-rocket","name":"B2b Rocket","category":"ai-marketing","subcategory":"cro-landing-pages","microcategory":null,"pricing_tier":"freemium","logo_url":"https://logo.clearbit.com/b2brocket.ai","logo_domain":"b2brocket.ai","website_url":"https://get.b2brocket.ai/plgxl20y3nqf","score_overall":56,"is_featured":false},{"slug":"backlink-management","name":"Backlink Management","category":"ai-marketing","subcategory":"social-media","microcategory":null,"pricing_tier":"freemium","logo_url":"https://logo.clearbit.com/backlinkmanagement.io","logo_domain":"backlinkmanagement.io","website_url":"https://backlinkmanagement.io","score_overall":58,"is_featured":false}]},"discovery":{"faq_items":[{"question":"Is Aysa Ai free?","answer":"Yes, Aysa Ai operates on a freemium model. This means users can access a free version with core functionalities, with options to upgrade for more advanced features and capabilities."}],"workflow_snippets":[{"title":"SEO Article Generation Workflow","use_case":"write seo articles","steps":["Step 1: Define target keywords and article topic within Aysa Ai.","Step 2: Aysa Ai's AI generates a complete, SEO-optimized article draft.","Step 3: Review the generated content and publish to improve rankings."],"time_saved":"2-3 hours per article"},{"title":"Automated Sales Outreach","use_case":"Automate sales outreach and lead gen with Aysa Ai","steps":["Step 1: Set parameters for lead generation and outreach campaigns.","Step 2: Aysa Ai identifies potential leads and drafts personalized outreach messages.","Step 3: Automate sending and track engagement for new sales opportunities."],"time_saved":"4-5 hours per campaign"}]},"audience":{"best_for_profiles":[{"profile":"E-commerce business owners","reason":"Because Aysa Ai is SaaS SEO automation software specifically for e-commerce, using AI to boost traffic and sales."},{"profile":"Digital marketing managers in e-commerce","reason":"Because it automates SEO content creation and improves content rankings, directly supporting marketing goals."}]}}