{"slug":"make-real-by-tldraw","route":"/tools/make-real-by-tldraw","index":true,"seo":{"title":"Make Real — AI Research Tool","description":"Make Real: AI-powered tool to convert UI drawings into functional websites using tldraw. Accelerate research and study with Make Real. Free plan available.","schema_types":["SoftwareApplication","Product"]},"hero":{"name":"Make Real","tagline":"AI summarization tool to Accelerate research and study with Make Real","logo_url":"https://logo.clearbit.com/tldraw.com","logo_domain":"tldraw.com","website_url":"https://makereal.tldraw.com","pricing_tier":"freemium","score_overall":38,"is_featured":false},"taxonomy":{"category":"ai-research","subcategory":null,"microcategory":null,"use_cases":["Accelerate research and study with Make Real"],"capabilities":["summarization","search"],"industries":[],"integrations":["make"],"ai_models":[],"platforms":["Web"],"audiences":["Designers"],"skill_levels":[]},"commercial":{"pricing_tier":"freemium","freemium":true,"free_trial":false,"affiliate_url":null,"partnerstack_match":false,"pricing_url":null,"signup_url":null,"monetization_score":0},"reviews":{"rating_average":null,"review_count_total":null,"g2_rating":null,"capterra_rating":null},"scores":{"overall":38,"content_readiness":78,"compare_value":null,"bestof_value":null,"beginner_fit":null,"integration_strength":null,"taxonomy_confidence":38},"content":{"description":"AI-powered tool to convert UI drawings into functional websites using tldraw.","tags":["research","study-tools","summaries","Summarization"],"feature_tags":[]},"related":{"related_tools":[{"slug":"arxivpaperai","name":"Arxivpaperai","category":"ai-research","subcategory":null,"microcategory":null,"pricing_tier":"freemium","logo_url":"https://logo.clearbit.com/arxivpaperai.com","logo_domain":"arxivpaperai.com","website_url":"https://www.arxivpaperai.com","score_overall":46,"is_featured":false},{"slug":"summer","name":"Summer","category":"ai-research","subcategory":null,"microcategory":null,"pricing_tier":"freemium","logo_url":"https://logo.clearbit.com/getsummer.ai","logo_domain":"getsummer.ai","website_url":"https://getsummer.ai","score_overall":46,"is_featured":false},{"slug":"video-summary-ai","name":"Video Summary Ai","category":"ai-research","subcategory":null,"microcategory":null,"pricing_tier":"freemium","logo_url":"https://logo.clearbit.com/videosummaryai.co","logo_domain":"videosummaryai.co","website_url":"https://videosummaryai.co","score_overall":49,"is_featured":false},{"slug":"aceify-ai","name":"Aceify Ai","category":"ai-research","subcategory":null,"microcategory":null,"pricing_tier":"freemium","logo_url":"https://logo.clearbit.com/aceify.ai","logo_domain":"aceify.ai","website_url":"https://aceify.ai","score_overall":43,"is_featured":false},{"slug":"doctrina-ai-website","name":"Doctrina Ai Website","category":"ai-research","subcategory":null,"microcategory":null,"pricing_tier":"freemium","logo_url":"https://logo.clearbit.com/doctrina-ai.com","logo_domain":"doctrina-ai.com","website_url":"https://doctrina-ai.com","score_overall":44,"is_featured":false},{"slug":"knowee-ai","name":"Knowee Ai","category":"ai-research","subcategory":null,"microcategory":null,"pricing_tier":"freemium","logo_url":"https://logo.clearbit.com/knowee.ai","logo_domain":"knowee.ai","website_url":"https://knowee.ai","score_overall":43,"is_featured":false},{"slug":"sumazon-com","name":"Sumazon","category":"ai-research","subcategory":null,"microcategory":null,"pricing_tier":"freemium","logo_url":"https://logo.clearbit.com/sumazon.com","logo_domain":"sumazon.com","website_url":"https://sumazon.com","score_overall":43,"is_featured":false},{"slug":"thelio","name":"Thelio","category":"ai-research","subcategory":null,"microcategory":null,"pricing_tier":"freemium","logo_url":"https://logo.clearbit.com/thelioai.com","logo_domain":"thelioai.com","website_url":"https://www.thelioai.com","score_overall":46,"is_featured":false}],"compare_candidates":[{"slug":"arxivpaperai","name":"Arxivpaperai","category":"ai-research","subcategory":null,"microcategory":null,"pricing_tier":"freemium","logo_url":"https://logo.clearbit.com/arxivpaperai.com","logo_domain":"arxivpaperai.com","website_url":"https://www.arxivpaperai.com","score_overall":46,"is_featured":false},{"slug":"summer","name":"Summer","category":"ai-research","subcategory":null,"microcategory":null,"pricing_tier":"freemium","logo_url":"https://logo.clearbit.com/getsummer.ai","logo_domain":"getsummer.ai","website_url":"https://getsummer.ai","score_overall":46,"is_featured":false},{"slug":"video-summary-ai","name":"Video Summary Ai","category":"ai-research","subcategory":null,"microcategory":null,"pricing_tier":"freemium","logo_url":"https://logo.clearbit.com/videosummaryai.co","logo_domain":"videosummaryai.co","website_url":"https://videosummaryai.co","score_overall":49,"is_featured":false},{"slug":"aceify-ai","name":"Aceify Ai","category":"ai-research","subcategory":null,"microcategory":null,"pricing_tier":"freemium","logo_url":"https://logo.clearbit.com/aceify.ai","logo_domain":"aceify.ai","website_url":"https://aceify.ai","score_overall":43,"is_featured":false},{"slug":"doctrina-ai-website","name":"Doctrina Ai Website","category":"ai-research","subcategory":null,"microcategory":null,"pricing_tier":"freemium","logo_url":"https://logo.clearbit.com/doctrina-ai.com","logo_domain":"doctrina-ai.com","website_url":"https://doctrina-ai.com","score_overall":44,"is_featured":false},{"slug":"knowee-ai","name":"Knowee Ai","category":"ai-research","subcategory":null,"microcategory":null,"pricing_tier":"freemium","logo_url":"https://logo.clearbit.com/knowee.ai","logo_domain":"knowee.ai","website_url":"https://knowee.ai","score_overall":43,"is_featured":false}],"alternatives":[{"slug":"arxivpaperai","name":"Arxivpaperai","category":"ai-research","subcategory":null,"microcategory":null,"pricing_tier":"freemium","logo_url":"https://logo.clearbit.com/arxivpaperai.com","logo_domain":"arxivpaperai.com","website_url":"https://www.arxivpaperai.com","score_overall":46,"is_featured":false},{"slug":"summer","name":"Summer","category":"ai-research","subcategory":null,"microcategory":null,"pricing_tier":"freemium","logo_url":"https://logo.clearbit.com/getsummer.ai","logo_domain":"getsummer.ai","website_url":"https://getsummer.ai","score_overall":46,"is_featured":false},{"slug":"video-summary-ai","name":"Video Summary Ai","category":"ai-research","subcategory":null,"microcategory":null,"pricing_tier":"freemium","logo_url":"https://logo.clearbit.com/videosummaryai.co","logo_domain":"videosummaryai.co","website_url":"https://videosummaryai.co","score_overall":49,"is_featured":false},{"slug":"aceify-ai","name":"Aceify Ai","category":"ai-research","subcategory":null,"microcategory":null,"pricing_tier":"freemium","logo_url":"https://logo.clearbit.com/aceify.ai","logo_domain":"aceify.ai","website_url":"https://aceify.ai","score_overall":43,"is_featured":false},{"slug":"doctrina-ai-website","name":"Doctrina Ai Website","category":"ai-research","subcategory":null,"microcategory":null,"pricing_tier":"freemium","logo_url":"https://logo.clearbit.com/doctrina-ai.com","logo_domain":"doctrina-ai.com","website_url":"https://doctrina-ai.com","score_overall":44,"is_featured":false},{"slug":"knowee-ai","name":"Knowee Ai","category":"ai-research","subcategory":null,"microcategory":null,"pricing_tier":"freemium","logo_url":"https://logo.clearbit.com/knowee.ai","logo_domain":"knowee.ai","website_url":"https://knowee.ai","score_overall":43,"is_featured":false}]}}