{"slug":"paraphraser-io","route":"/tools/paraphraser-io","index":true,"seo":{"title":"Paraphraser — AI Writing Tool","description":"Paraphraser: AI-powered paraphrasing tool with multiple modes and additional writing utilities. Free plan available.","schema_types":["SoftwareApplication","Product"]},"hero":{"name":"Paraphraser","tagline":"AI text generation tool to write blog posts","logo_url":"https://logo.clearbit.com/paraphraser.io","logo_domain":"paraphraser.io","website_url":"https://www.paraphraser.io/plagiarism-checker","pricing_tier":"freemium","score_overall":48,"is_featured":false},"taxonomy":{"category":"ai-writing","subcategory":"blog-writers","microcategory":null,"use_cases":["write-blog-posts","Write blog posts and articles with Paraphraser","Create and optimise ad campaigns with Paraphraser"],"capabilities":["text-generation","rewriting"],"industries":["hr","HR & Recruiting"],"integrations":[],"ai_models":[],"platforms":["Web"],"audiences":["Content Creators","HR Teams"],"skill_levels":[]},"commercial":{"pricing_tier":"freemium","freemium":true,"free_trial":false,"affiliate_url":null,"partnerstack_match":false,"pricing_url":null,"signup_url":null,"monetization_score":0},"reviews":{"rating_average":null,"review_count_total":null,"g2_rating":null,"capterra_rating":null},"scores":{"overall":48,"content_readiness":100,"compare_value":null,"bestof_value":null,"beginner_fit":null,"integration_strength":null,"taxonomy_confidence":63},"content":{"description":"AI-powered paraphrasing tool with multiple modes and additional writing utilities.","tags":["hr","marketing","Text Generation","Writing Assistant"],"feature_tags":[]},"related":{"related_tools":[{"slug":"paraphraser","name":"Paraphraser","category":"ai-writing","subcategory":"blog-writers","microcategory":null,"pricing_tier":"freemium","logo_url":"https://logo.clearbit.com/paraphrasetool.com","logo_domain":"paraphrasetool.com","website_url":"https://paraphrasetool.com/","score_overall":49,"is_featured":false},{"slug":"autoseo","name":"Autoseo","category":"ai-writing","subcategory":"blog-writers","microcategory":null,"pricing_tier":"freemium","logo_url":"https://logo.clearbit.com/auto-seo.ai","logo_domain":"auto-seo.ai","website_url":"https://auto-seo.ai","score_overall":53,"is_featured":false},{"slug":"i-am-now-keyboard-rephraser","name":"I Am Now Keyboard Rephraser","category":"ai-writing","subcategory":"blog-writers","microcategory":null,"pricing_tier":"freemium","logo_url":"https://logo.clearbit.com/iamnow.app","logo_domain":"iamnow.app","website_url":"https://iamnow.app","score_overall":50,"is_featured":false},{"slug":"ibiling-cn","name":"Ibiling Cn","category":"ai-writing","subcategory":"blog-writers","microcategory":null,"pricing_tier":"freemium","logo_url":"https://logo.clearbit.com/ibiling.cn","logo_domain":"ibiling.cn","website_url":"https://ibiling.cn","score_overall":48,"is_featured":false},{"slug":"quetext-com","name":"Quetext","category":"ai-writing","subcategory":"blog-writers","microcategory":null,"pricing_tier":"freemium","logo_url":"https://logo.clearbit.com/quetext.com","logo_domain":"quetext.com","website_url":"https://quetext.com","score_overall":49,"is_featured":false},{"slug":"rephrasely","name":"Rephrasely","category":"ai-writing","subcategory":"blog-writers","microcategory":null,"pricing_tier":"freemium","logo_url":"https://logo.clearbit.com/rephrasely.com","logo_domain":"rephrasely.com","website_url":"https://rephrasely.com","score_overall":49,"is_featured":false},{"slug":"reword","name":"Reword","category":"ai-writing","subcategory":"blog-writers","microcategory":null,"pricing_tier":"freemium","logo_url":"https://logo.clearbit.com/reword.co","logo_domain":"reword.co","website_url":"https://reword.co","score_overall":50,"is_featured":false},{"slug":"smartstudi-com","name":"Smartstudi","category":"ai-writing","subcategory":"blog-writers","microcategory":null,"pricing_tier":"freemium","logo_url":"https://logo.clearbit.com/smartstudi.com","logo_domain":"smartstudi.com","website_url":"https://smartstudi.com","score_overall":52,"is_featured":false}],"compare_candidates":[{"slug":"paraphraser","name":"Paraphraser","category":"ai-writing","subcategory":"blog-writers","microcategory":null,"pricing_tier":"freemium","logo_url":"https://logo.clearbit.com/paraphrasetool.com","logo_domain":"paraphrasetool.com","website_url":"https://paraphrasetool.com/","score_overall":49,"is_featured":false},{"slug":"autoseo","name":"Autoseo","category":"ai-writing","subcategory":"blog-writers","microcategory":null,"pricing_tier":"freemium","logo_url":"https://logo.clearbit.com/auto-seo.ai","logo_domain":"auto-seo.ai","website_url":"https://auto-seo.ai","score_overall":53,"is_featured":false},{"slug":"i-am-now-keyboard-rephraser","name":"I Am Now Keyboard Rephraser","category":"ai-writing","subcategory":"blog-writers","microcategory":null,"pricing_tier":"freemium","logo_url":"https://logo.clearbit.com/iamnow.app","logo_domain":"iamnow.app","website_url":"https://iamnow.app","score_overall":50,"is_featured":false},{"slug":"ibiling-cn","name":"Ibiling Cn","category":"ai-writing","subcategory":"blog-writers","microcategory":null,"pricing_tier":"freemium","logo_url":"https://logo.clearbit.com/ibiling.cn","logo_domain":"ibiling.cn","website_url":"https://ibiling.cn","score_overall":48,"is_featured":false},{"slug":"quetext-com","name":"Quetext","category":"ai-writing","subcategory":"blog-writers","microcategory":null,"pricing_tier":"freemium","logo_url":"https://logo.clearbit.com/quetext.com","logo_domain":"quetext.com","website_url":"https://quetext.com","score_overall":49,"is_featured":false},{"slug":"rephrasely","name":"Rephrasely","category":"ai-writing","subcategory":"blog-writers","microcategory":null,"pricing_tier":"freemium","logo_url":"https://logo.clearbit.com/rephrasely.com","logo_domain":"rephrasely.com","website_url":"https://rephrasely.com","score_overall":49,"is_featured":false}],"alternatives":[{"slug":"paraphraser","name":"Paraphraser","category":"ai-writing","subcategory":"blog-writers","microcategory":null,"pricing_tier":"freemium","logo_url":"https://logo.clearbit.com/paraphrasetool.com","logo_domain":"paraphrasetool.com","website_url":"https://paraphrasetool.com/","score_overall":49,"is_featured":false},{"slug":"autoseo","name":"Autoseo","category":"ai-writing","subcategory":"blog-writers","microcategory":null,"pricing_tier":"freemium","logo_url":"https://logo.clearbit.com/auto-seo.ai","logo_domain":"auto-seo.ai","website_url":"https://auto-seo.ai","score_overall":53,"is_featured":false},{"slug":"i-am-now-keyboard-rephraser","name":"I Am Now Keyboard Rephraser","category":"ai-writing","subcategory":"blog-writers","microcategory":null,"pricing_tier":"freemium","logo_url":"https://logo.clearbit.com/iamnow.app","logo_domain":"iamnow.app","website_url":"https://iamnow.app","score_overall":50,"is_featured":false},{"slug":"ibiling-cn","name":"Ibiling Cn","category":"ai-writing","subcategory":"blog-writers","microcategory":null,"pricing_tier":"freemium","logo_url":"https://logo.clearbit.com/ibiling.cn","logo_domain":"ibiling.cn","website_url":"https://ibiling.cn","score_overall":48,"is_featured":false},{"slug":"quetext-com","name":"Quetext","category":"ai-writing","subcategory":"blog-writers","microcategory":null,"pricing_tier":"freemium","logo_url":"https://logo.clearbit.com/quetext.com","logo_domain":"quetext.com","website_url":"https://quetext.com","score_overall":49,"is_featured":false},{"slug":"rephrasely","name":"Rephrasely","category":"ai-writing","subcategory":"blog-writers","microcategory":null,"pricing_tier":"freemium","logo_url":"https://logo.clearbit.com/rephrasely.com","logo_domain":"rephrasely.com","website_url":"https://rephrasely.com","score_overall":49,"is_featured":false}]}}