{"slug":"translate-video","route":"/tools/translate-video","index":true,"seo":{"title":"Translate Video — AI Translation Tool","description":"Translate Video: AI-powered video translation, captioning, dubbing, and voice-over in 75+ languages. Free plan available.","schema_types":["SoftwareApplication","Product"]},"hero":{"name":"Translate Video","tagline":"AI translation tool to translate videos","logo_url":"https://logo.clearbit.com/translate.video","logo_domain":"translate.video","website_url":"https://www.translate.video","pricing_tier":"freemium","score_overall":43,"is_featured":false},"taxonomy":{"category":"ai-writing","subcategory":"script-writing","microcategory":null,"use_cases":["translate-videos","generate-youtube-scripts","Write and produce video scripts with Translate Video","Translate content across languages with Translate Video","Generate AI voiceovers and narrations with Translate Video"],"capabilities":["translation","video-dubbing"],"industries":["media"],"integrations":[],"ai_models":[],"platforms":["Web"],"audiences":["Business Owners"],"skill_levels":[]},"commercial":{"pricing_tier":"freemium","freemium":true,"free_trial":false,"affiliate_url":null,"partnerstack_match":false,"pricing_url":null,"signup_url":null,"monetization_score":0},"reviews":{"rating_average":null,"review_count_total":null,"g2_rating":null,"capterra_rating":null},"scores":{"overall":43,"content_readiness":100,"compare_value":null,"bestof_value":null,"beginner_fit":null,"integration_strength":null,"taxonomy_confidence":67},"content":{"description":"AI-powered video translation, captioning, dubbing, and voice-over in 75+ languages.","tags":["translation","voiceover","bi","localization","Translation"],"feature_tags":[]},"related":{"related_tools":[{"slug":"chatscribe-pro","name":"Chatscribe Pro","category":"ai-writing","subcategory":"blog-writers","microcategory":null,"pricing_tier":"freemium","logo_url":"https://logo.clearbit.com/chatscribe.pro","logo_domain":"chatscribe.pro","website_url":"https://chatscribe.pro","score_overall":48,"is_featured":false},{"slug":"apolloai","name":"Apolloai","category":"ai-writing","subcategory":"blog-writers","microcategory":null,"pricing_tier":"freemium","logo_url":"https://logo.clearbit.com/useapollo.app","logo_domain":"useapollo.app","website_url":"https://useapollo.app","score_overall":49,"is_featured":false},{"slug":"autoscript-fr","name":"Autoscript Fr","category":"ai-writing","subcategory":"blog-writers","microcategory":null,"pricing_tier":"freemium","logo_url":"https://logo.clearbit.com/autoscript.fr","logo_domain":"autoscript.fr","website_url":"https://autoscript.fr","score_overall":51,"is_featured":false},{"slug":"axofy-ai","name":"Axofy Ai","category":"ai-writing","subcategory":"blog-writers","microcategory":null,"pricing_tier":"freemium","logo_url":"https://logo.clearbit.com/axofy.ai","logo_domain":"axofy.ai","website_url":"https://axofy.ai","score_overall":48,"is_featured":false},{"slug":"basedlabs","name":"Basedlabs","category":"ai-writing","subcategory":"blog-writers","microcategory":null,"pricing_tier":"freemium","logo_url":"https://logo.clearbit.com/basedlabs.ai","logo_domain":"basedlabs.ai","website_url":"https://www.basedlabs.ai/","score_overall":48,"is_featured":false},{"slug":"blaze-designer","name":"Blaze Designer","category":"ai-writing","subcategory":"blog-writers","microcategory":null,"pricing_tier":"freemium","logo_url":"https://logo.clearbit.com/blaze.ai","logo_domain":"blaze.ai","website_url":"https://www.blaze.ai","score_overall":50,"is_featured":false},{"slug":"blogmyvideo","name":"Blogmyvideo","category":"ai-writing","subcategory":"blog-writers","microcategory":null,"pricing_tier":"freemium","logo_url":"https://logo.clearbit.com/blogmyvideo.com","logo_domain":"blogmyvideo.com","website_url":"https://blogmyvideo.com","score_overall":48,"is_featured":false},{"slug":"boolv","name":"Boolv","category":"ai-writing","subcategory":"blog-writers","microcategory":null,"pricing_tier":"freemium","logo_url":"https://logo.clearbit.com/boolv.tech","logo_domain":"boolv.tech","website_url":"https://booltool.boolv.tech/","score_overall":48,"is_featured":false}],"compare_candidates":[{"slug":"chatscribe-pro","name":"Chatscribe Pro","category":"ai-writing","subcategory":"blog-writers","microcategory":null,"pricing_tier":"freemium","logo_url":"https://logo.clearbit.com/chatscribe.pro","logo_domain":"chatscribe.pro","website_url":"https://chatscribe.pro","score_overall":48,"is_featured":false},{"slug":"apolloai","name":"Apolloai","category":"ai-writing","subcategory":"blog-writers","microcategory":null,"pricing_tier":"freemium","logo_url":"https://logo.clearbit.com/useapollo.app","logo_domain":"useapollo.app","website_url":"https://useapollo.app","score_overall":49,"is_featured":false},{"slug":"autoscript-fr","name":"Autoscript Fr","category":"ai-writing","subcategory":"blog-writers","microcategory":null,"pricing_tier":"freemium","logo_url":"https://logo.clearbit.com/autoscript.fr","logo_domain":"autoscript.fr","website_url":"https://autoscript.fr","score_overall":51,"is_featured":false},{"slug":"axofy-ai","name":"Axofy Ai","category":"ai-writing","subcategory":"blog-writers","microcategory":null,"pricing_tier":"freemium","logo_url":"https://logo.clearbit.com/axofy.ai","logo_domain":"axofy.ai","website_url":"https://axofy.ai","score_overall":48,"is_featured":false},{"slug":"basedlabs","name":"Basedlabs","category":"ai-writing","subcategory":"blog-writers","microcategory":null,"pricing_tier":"freemium","logo_url":"https://logo.clearbit.com/basedlabs.ai","logo_domain":"basedlabs.ai","website_url":"https://www.basedlabs.ai/","score_overall":48,"is_featured":false},{"slug":"blaze-designer","name":"Blaze Designer","category":"ai-writing","subcategory":"blog-writers","microcategory":null,"pricing_tier":"freemium","logo_url":"https://logo.clearbit.com/blaze.ai","logo_domain":"blaze.ai","website_url":"https://www.blaze.ai","score_overall":50,"is_featured":false}],"alternatives":[{"slug":"chatscribe-pro","name":"Chatscribe Pro","category":"ai-writing","subcategory":"blog-writers","microcategory":null,"pricing_tier":"freemium","logo_url":"https://logo.clearbit.com/chatscribe.pro","logo_domain":"chatscribe.pro","website_url":"https://chatscribe.pro","score_overall":48,"is_featured":false},{"slug":"apolloai","name":"Apolloai","category":"ai-writing","subcategory":"blog-writers","microcategory":null,"pricing_tier":"freemium","logo_url":"https://logo.clearbit.com/useapollo.app","logo_domain":"useapollo.app","website_url":"https://useapollo.app","score_overall":49,"is_featured":false},{"slug":"autoscript-fr","name":"Autoscript Fr","category":"ai-writing","subcategory":"blog-writers","microcategory":null,"pricing_tier":"freemium","logo_url":"https://logo.clearbit.com/autoscript.fr","logo_domain":"autoscript.fr","website_url":"https://autoscript.fr","score_overall":51,"is_featured":false},{"slug":"axofy-ai","name":"Axofy Ai","category":"ai-writing","subcategory":"blog-writers","microcategory":null,"pricing_tier":"freemium","logo_url":"https://logo.clearbit.com/axofy.ai","logo_domain":"axofy.ai","website_url":"https://axofy.ai","score_overall":48,"is_featured":false},{"slug":"basedlabs","name":"Basedlabs","category":"ai-writing","subcategory":"blog-writers","microcategory":null,"pricing_tier":"freemium","logo_url":"https://logo.clearbit.com/basedlabs.ai","logo_domain":"basedlabs.ai","website_url":"https://www.basedlabs.ai/","score_overall":48,"is_featured":false},{"slug":"blaze-designer","name":"Blaze Designer","category":"ai-writing","subcategory":"blog-writers","microcategory":null,"pricing_tier":"freemium","logo_url":"https://logo.clearbit.com/blaze.ai","logo_domain":"blaze.ai","website_url":"https://www.blaze.ai","score_overall":50,"is_featured":false}]}}