{"slug":"wondera-ai","route":"/tools/wondera-ai","index":true,"seo":{"title":"Wondera Ai — AI Audio Tool","description":"Wondera Ai: Wondera is an AI-powered music creation platform that lets anyone write, produce, and publish songs through natural… Free plan available.","schema_types":["SoftwareApplication","Product"]},"hero":{"name":"Wondera Ai","tagline":"AI debugging tool to debug code","logo_url":"https://logo.clearbit.com/wondera.ai","logo_domain":"wondera.ai","website_url":"https://www.wondera.ai","pricing_tier":"freemium","score_overall":48,"is_featured":false},"taxonomy":{"category":"ai-audio-voice","subcategory":"speech-to-text","microcategory":null,"use_cases":["debug-code","Transcribe audio and video files with Wondera Ai","Generate, review and debug code with Wondera Ai"],"capabilities":["debugging"],"industries":["hr","creator-economy","manufacturing","software-development"],"integrations":[],"ai_models":[],"platforms":["Web"],"audiences":["Developers","Content Creators","HR Teams"],"skill_levels":[]},"commercial":{"pricing_tier":"freemium","freemium":true,"free_trial":false,"affiliate_url":null,"partnerstack_match":false,"pricing_url":null,"signup_url":null,"monetization_score":0},"reviews":{"rating_average":null,"review_count_total":null,"g2_rating":null,"capterra_rating":null},"scores":{"overall":48,"content_readiness":100,"compare_value":null,"bestof_value":null,"beginner_fit":null,"integration_strength":null,"taxonomy_confidence":60},"content":{"description":"Wondera is an AI-powered music creation platform that lets anyone write, produce, and publish songs through natural conversations. Combining proprietary models and real production tools, it's ideal for creators, developers, and innovators exploring generative AI in music.","tags":["developers","bi","hr","creator-economy","Music & Audio"],"feature_tags":[]},"related":{"related_tools":[{"slug":"ai-generating-ultimate-ai-generator","name":"Ai Generating Ultimate Ai Generator","category":"ai-audio-voice","subcategory":"speech-to-text","microcategory":null,"pricing_tier":"freemium","logo_url":"https://logo.clearbit.com/aigenerating.online","logo_domain":"aigenerating.online","website_url":"https://aigenerating.online","score_overall":45,"is_featured":false},{"slug":"landrific-ai","name":"Landrific Ai","category":"ai-audio-voice","subcategory":"speech-to-text","microcategory":null,"pricing_tier":"freemium","logo_url":"https://logo.clearbit.com/landrific.online","logo_domain":"landrific.online","website_url":"https://landrific.online","score_overall":43,"is_featured":false},{"slug":"swiftfox-ai","name":"Swiftfox Ai","category":"ai-audio-voice","subcategory":"speech-to-text","microcategory":"podcast-transcription","pricing_tier":"freemium","logo_url":"https://logo.clearbit.com/swiftfox.ai","logo_domain":"swiftfox.ai","website_url":"https://swiftfox.ai","score_overall":47,"is_featured":false},{"slug":"008","name":"008","category":"ai-audio-voice","subcategory":"speech-to-text","microcategory":"meeting-transcription","pricing_tier":"free","logo_url":"https://logo.clearbit.com/008agent.ai","logo_domain":"008agent.ai","website_url":"https://008agent.ai","score_overall":45,"is_featured":false},{"slug":"1-ai-speech-video-to-text-tool","name":"1 Ai Speech Video To Text","category":"ai-audio-voice","subcategory":"speech-to-text","microcategory":null,"pricing_tier":"freemium","logo_url":"https://logo.clearbit.com/videotowords.ai","logo_domain":"videotowords.ai","website_url":"https://www.videotowords.ai/","score_overall":45,"is_featured":false},{"slug":"accuratescribe-ai","name":"Accuratescribe Ai","category":"ai-audio-voice","subcategory":"speech-to-text","microcategory":null,"pricing_tier":"freemium","logo_url":"https://logo.clearbit.com/accuratescribe.ai","logo_domain":"accuratescribe.ai","website_url":"https://accuratescribe.ai","score_overall":45,"is_featured":false},{"slug":"agilotext","name":"Agilotext","category":"ai-audio-voice","subcategory":"speech-to-text","microcategory":null,"pricing_tier":"freemium","logo_url":"https://logo.clearbit.com/agilotext.com","logo_domain":"agilotext.com","website_url":"https://www.agilotext.com","score_overall":43,"is_featured":false},{"slug":"ai-audio-kit","name":"Ai Audio Kit","category":"ai-audio-voice","subcategory":"speech-to-text","microcategory":"podcast-transcription","pricing_tier":"freemium","logo_url":"https://logo.clearbit.com/pages.dev","logo_domain":"pages.dev","website_url":"https://aiaudiokit.pages.dev","score_overall":46,"is_featured":false}],"compare_candidates":[{"slug":"ai-generating-ultimate-ai-generator","name":"Ai Generating Ultimate Ai Generator","category":"ai-audio-voice","subcategory":"speech-to-text","microcategory":null,"pricing_tier":"freemium","logo_url":"https://logo.clearbit.com/aigenerating.online","logo_domain":"aigenerating.online","website_url":"https://aigenerating.online","score_overall":45,"is_featured":false},{"slug":"landrific-ai","name":"Landrific Ai","category":"ai-audio-voice","subcategory":"speech-to-text","microcategory":null,"pricing_tier":"freemium","logo_url":"https://logo.clearbit.com/landrific.online","logo_domain":"landrific.online","website_url":"https://landrific.online","score_overall":43,"is_featured":false},{"slug":"swiftfox-ai","name":"Swiftfox Ai","category":"ai-audio-voice","subcategory":"speech-to-text","microcategory":"podcast-transcription","pricing_tier":"freemium","logo_url":"https://logo.clearbit.com/swiftfox.ai","logo_domain":"swiftfox.ai","website_url":"https://swiftfox.ai","score_overall":47,"is_featured":false},{"slug":"008","name":"008","category":"ai-audio-voice","subcategory":"speech-to-text","microcategory":"meeting-transcription","pricing_tier":"free","logo_url":"https://logo.clearbit.com/008agent.ai","logo_domain":"008agent.ai","website_url":"https://008agent.ai","score_overall":45,"is_featured":false},{"slug":"1-ai-speech-video-to-text-tool","name":"1 Ai Speech Video To Text","category":"ai-audio-voice","subcategory":"speech-to-text","microcategory":null,"pricing_tier":"freemium","logo_url":"https://logo.clearbit.com/videotowords.ai","logo_domain":"videotowords.ai","website_url":"https://www.videotowords.ai/","score_overall":45,"is_featured":false},{"slug":"accuratescribe-ai","name":"Accuratescribe Ai","category":"ai-audio-voice","subcategory":"speech-to-text","microcategory":null,"pricing_tier":"freemium","logo_url":"https://logo.clearbit.com/accuratescribe.ai","logo_domain":"accuratescribe.ai","website_url":"https://accuratescribe.ai","score_overall":45,"is_featured":false}],"alternatives":[{"slug":"ai-generating-ultimate-ai-generator","name":"Ai Generating Ultimate Ai Generator","category":"ai-audio-voice","subcategory":"speech-to-text","microcategory":null,"pricing_tier":"freemium","logo_url":"https://logo.clearbit.com/aigenerating.online","logo_domain":"aigenerating.online","website_url":"https://aigenerating.online","score_overall":45,"is_featured":false},{"slug":"landrific-ai","name":"Landrific Ai","category":"ai-audio-voice","subcategory":"speech-to-text","microcategory":null,"pricing_tier":"freemium","logo_url":"https://logo.clearbit.com/landrific.online","logo_domain":"landrific.online","website_url":"https://landrific.online","score_overall":43,"is_featured":false},{"slug":"swiftfox-ai","name":"Swiftfox Ai","category":"ai-audio-voice","subcategory":"speech-to-text","microcategory":"podcast-transcription","pricing_tier":"freemium","logo_url":"https://logo.clearbit.com/swiftfox.ai","logo_domain":"swiftfox.ai","website_url":"https://swiftfox.ai","score_overall":47,"is_featured":false},{"slug":"008","name":"008","category":"ai-audio-voice","subcategory":"speech-to-text","microcategory":"meeting-transcription","pricing_tier":"free","logo_url":"https://logo.clearbit.com/008agent.ai","logo_domain":"008agent.ai","website_url":"https://008agent.ai","score_overall":45,"is_featured":false},{"slug":"1-ai-speech-video-to-text-tool","name":"1 Ai Speech Video To Text","category":"ai-audio-voice","subcategory":"speech-to-text","microcategory":null,"pricing_tier":"freemium","logo_url":"https://logo.clearbit.com/videotowords.ai","logo_domain":"videotowords.ai","website_url":"https://www.videotowords.ai/","score_overall":45,"is_featured":false},{"slug":"accuratescribe-ai","name":"Accuratescribe Ai","category":"ai-audio-voice","subcategory":"speech-to-text","microcategory":null,"pricing_tier":"freemium","logo_url":"https://logo.clearbit.com/accuratescribe.ai","logo_domain":"accuratescribe.ai","website_url":"https://accuratescribe.ai","score_overall":45,"is_featured":false}]}}